flask_fixtures/__init__.py
flask_fixtures/loaders.py
flask_fixtures/utils.py
Flask_Fixtures-0.3.8.dist-info/LICENSE
Flask_Fixtures-0.3.8.dist-info/METADATA
Flask_Fixtures-0.3.8.dist-info/WHEEL
Flask_Fixtures-0.3.8.dist-info/top_level.txt
Flask_Fixtures-0.3.8.dist-info/RECORD
