Metadata-Version: 2.1
Name: Flask-Fixtures
Version: 0.3.8
Summary: A simple library for adding database fixtures for unit tests using nothing but JSON or YAML.
Home-page: https://github.com/croach/Flask-Fixtures
Author: Christopher Roach
Author-email: vthakr@gmail.com
Maintainer: Christopher Roach
Maintainer-email: vthakr@gmail.com
License: MIT License
Platform: any
Classifier: Development Status :: 3 - Alpha
Classifier: Environment :: Web Environment
Classifier: Intended Audience :: Developers
Classifier: License :: OSI Approved :: Apache Software License
Classifier: Operating System :: OS Independent
Classifier: Programming Language :: Python
Classifier: Topic :: Internet :: WWW/HTTP :: Dynamic Content
Classifier: Topic :: Software Development :: Libraries :: Python Modules
Classifier: Topic :: Software Development :: Testing
Requires-Dist: Flask
Requires-Dist: Flask-SQLAlchemy
Requires-Dist: six
